LICENSE
README.md
requirements.txt
setup.py
fromconfig_yarn/__init__.py
fromconfig_yarn/launcher.py
fromconfig_yarn/version.py
fromconfig_yarn.egg-info/PKG-INFO
fromconfig_yarn.egg-info/SOURCES.txt
fromconfig_yarn.egg-info/dependency_links.txt
fromconfig_yarn.egg-info/entry_points.txt
fromconfig_yarn.egg-info/requires.txt
fromconfig_yarn.egg-info/top_level.txt
tests/__init__.py
tests/unit/__init__.py
tests/unit/test_launcher.py
tests/unit/test_version.py