Metadata-Version: 2.1
Name: fromconfig-yarn
Version: 0.1.3
Summary: # FromConfig Yarn
Home-page: https://github.com/criteo/fromconfig-yarn
Author: Criteo
License: UNKNOWN
Platform: UNKNOWN
Classifier: License :: OSI Approved :: Apache Software License
Classifier: Operating System :: OS Independent
Classifier: Programming Language :: Python :: 3
Classifier: Programming Language :: Python :: 3.6
Classifier: Intended Audience :: Developers
License-File: LICENSE
